LICENSE
MANIFEST.in
README.md
requirements.txt
setup.py
scandy/__init__.py
scandy.egg-info/PKG-INFO
scandy.egg-info/SOURCES.txt
scandy.egg-info/dependency_links.txt
scandy.egg-info/requires.txt
scandy.egg-info/top_level.txt
scandy/models/__init__.py
scandy/models/model.py
scandy/models/objectfile.py
scandy/models/LocationModel/__init__.py
scandy/models/LocationModel/model.py
scandy/models/MixedModel/__init__.py
scandy/models/MixedModel/model.py
scandy/models/ObjectModel/__init__.py
scandy/models/ObjectModel/model.py
scandy/utils/__init__.py
scandy/utils/dataclass.py
scandy/utils/functions.py