Metadata-Version: 2.1
Name: scandy
Version: 0.0.3
Summary: Simulating Realistic Human Scanpaths in Dynamic Real-World Scenes
Home-page: https://github.com/rederoth/ScanDy
Author: Nicolas Roth
Author-email: roth@tu-berlin.de
License: MIT
Classifier: Programming Language :: Python :: 3
Classifier: License :: OSI Approved :: MIT License
Classifier: Operating System :: OS Independent
Requires-Python: >=3.6
License-File: LICENSE
